reco/__init__.py
reco/cross_validation/__init__.py
reco/cross_validation/cross_validation.py
reco/datasets/__init__.py
reco/datasets/load_datasets.py
reco/datasets/movielens100k.csv
reco/datasets/ml-100k/u.item
reco/datasets/ml-100k/u.user
reco/datasets/ml-100k/ua.base
reco/datasets/ml-100k/ua.test
reco/metrics/__init__.py
reco/metrics/metrics.py
reco/recommender/__init__.py
reco/recommender/cfilter.py
reco/recommender/fm.c
reco/recommender/fm.cp36-win_amd64.pyd
reco/recommender/funksvd.c
reco/recommender/funksvd.cp36-win_amd64.pyd
reco/recommender/similarity_algorithms.py
reco/recommender/svd.py
reco/recommender/utils.py
reco/recommender/widedeepnet.py
reco-0.2.1.dist-info/METADATA
reco-0.2.1.dist-info/RECORD
reco-0.2.1.dist-info/WHEEL
reco-0.2.1.dist-info/top_level.txt
