Metadata-Version: 2.1
Name: reco
Version: 0.2.1
Summary: a simple yet powerful recommender systems library in python
Home-page: http://github.com/mayukh18/reco
Author: Mayukh Bhattacharyya
Author-email: mayukh.superb@gmail.com
License: MIT
Download-URL: https://github.com/mayukh18/reco/tarball/0.2.1
Keywords: recommendation
Platform: UNKNOWN
Requires-Dist: numpy
Requires-Dist: pandas
